airflow_spark_on_k8s_job_builder/__init__.py
airflow_spark_on_k8s_job_builder/constants.py
airflow_spark_on_k8s_job_builder/core.py
airflow_spark_on_k8s_job_builder/customizable_spark_k8s_operator.py
airflow_spark_on_k8s_job_builder/default_spark_k8s_template.yaml
airflow_spark_on_k8s_job_builder-0.5.0.dist-info/licenses/LICENSE
airflow_spark_on_k8s_job_builder-0.5.0.dist-info/METADATA
airflow_spark_on_k8s_job_builder-0.5.0.dist-info/WHEEL
airflow_spark_on_k8s_job_builder-0.5.0.dist-info/top_level.txt
airflow_spark_on_k8s_job_builder-0.5.0.dist-info/RECORD
