Metadata-Version: 2.4
Name: airflow-spark-on-k8s-job-builder
Version: 0.5.0
Summary: A library to limit the amount of unnecessary boilerplate code required when launching Spark Jobs against k8s Spark-Operator in Airflow
Home-page: https://github.com/yourusername/my_library
Author: Stroeer Labs Data Engineering
Author-email: diogo.aurelio@stroeer.de
Classifier: Programming Language :: Python :: 3
Classifier: License :: OSI Approved :: MIT License
Classifier: Operating System :: OS Independent
Requires-Python: >=3.6
License-File: LICENSE
Dynamic: author
Dynamic: author-email
Dynamic: classifier
Dynamic: description
Dynamic: description-content-type
Dynamic: home-page
Dynamic: license-file
Dynamic: requires-python
Dynamic: summary
